ONCToolbox/__init__.py
ONCToolbox/core.py
ONCToolbox/qaqc.py
ONCToolbox/utils/__init__.py
ONCToolbox/utils/climatology.py
ONCToolbox/utils/core.py
ONCToolbox/utils/ferries.py
ONCToolbox/utils/locations.py
ONCToolbox/utils/profilers.py
ONCToolbox/utils/suna.py
ONCToolbox/utils/token.py
onc_toolbox-0.0.6.dist-info/licenses/LICENSE
onc_toolbox-0.0.6.dist-info/METADATA
onc_toolbox-0.0.6.dist-info/WHEEL
onc_toolbox-0.0.6.dist-info/top_level.txt
onc_toolbox-0.0.6.dist-info/RECORD
