Metadata-Version: 2.4
Name: onc-toolbox
Version: 0.0.6
Summary: A toolbox for exploring Ocean Networks Canada data for the adventuring scientist.
Author-email: Ian Black <iantimothyblack@gmail.com>
License-Expression: Apache-2.0
Project-URL: Repository, https://github.com/IanTBlack/onc-toolbox
Keywords: ONC
Classifier: Development Status :: 2 - Pre-Alpha
Classifier: Intended Audience :: Science/Research
Classifier: Topic :: Scientific/Engineering
Classifier: Programming Language :: Python :: 3.10
Classifier: Programming Language :: Python :: 3.11
Classifier: Programming Language :: Python :: 3.12
Classifier: Programming Language :: Python :: 3.13
Requires-Python: >=3.10
License-File: LICENSE
Requires-Dist: bottleneck
Requires-Dist: cartopy
Requires-Dist: echopype
Requires-Dist: gsw
Requires-Dist: jupyter
Requires-Dist: matplotlib
Requires-Dist: onc
Requires-Dist: netCDF4
Requires-Dist: numpy
Requires-Dist: pandas
Requires-Dist: requests
Requires-Dist: scipy
Requires-Dist: xarray
Requires-Dist: uv
Requires-Dist: pytest
Requires-Dist: ipykernel
Requires-Dist: ipympl
Dynamic: license-file
